llm_agent_toolkit/__init__.py
llm_agent_toolkit/_base.py
llm_agent_toolkit/_chunkers.py
llm_agent_toolkit/_core.py
llm_agent_toolkit/_encoder.py
llm_agent_toolkit/_loader.py
llm_agent_toolkit/_memory.py
llm_agent_toolkit/_tool.py
llm_agent_toolkit/_util.py
llm_agent_toolkit/chunkers/__init__.py
llm_agent_toolkit/chunkers/basic.py
llm_agent_toolkit/chunkers/hybrid.py
llm_agent_toolkit/chunkers/semantic.py
llm_agent_toolkit/chunkers/utility.py
llm_agent_toolkit/core/__init__.py
llm_agent_toolkit/core/deep_seek/__init__.py
llm_agent_toolkit/core/deep_seek/base.py
llm_agent_toolkit/core/deep_seek/reasoning.py
llm_agent_toolkit/core/deep_seek/t2t.py
llm_agent_toolkit/core/deep_seek/t2tso.py
llm_agent_toolkit/core/gemini/__init__.py
llm_agent_toolkit/core/gemini/base.py
llm_agent_toolkit/core/gemini/i2t.py
llm_agent_toolkit/core/gemini/i2t_w_tool.py
llm_agent_toolkit/core/gemini/so.py
llm_agent_toolkit/core/gemini/t2t.py
llm_agent_toolkit/core/gemini/t2t_w_tool.py
llm_agent_toolkit/core/gemini/thinking.py
llm_agent_toolkit/core/local/__init__.py
llm_agent_toolkit/core/local/base.py
llm_agent_toolkit/core/local/i2t.py
llm_agent_toolkit/core/local/i2tso.py
llm_agent_toolkit/core/local/t2t.py
llm_agent_toolkit/core/local/t2tso.py
llm_agent_toolkit/core/open_ai/__init__.py
llm_agent_toolkit/core/open_ai/base.py
llm_agent_toolkit/core/open_ai/i2t.py
llm_agent_toolkit/core/open_ai/reasoning.py
llm_agent_toolkit/core/open_ai/so.py
llm_agent_toolkit/core/open_ai/t2t.py
llm_agent_toolkit/encoder/__init__.py
llm_agent_toolkit/encoder/gemini.py
llm_agent_toolkit/encoder/local.py
llm_agent_toolkit/encoder/remote.py
llm_agent_toolkit/encoder/transformers_emb.py
llm_agent_toolkit/image_generator/__init__.py
llm_agent_toolkit/image_generator/base.py
llm_agent_toolkit/image_generator/open_ai/__init__.py
llm_agent_toolkit/image_generator/open_ai/t2i.py
llm_agent_toolkit/loader/__init__.py
llm_agent_toolkit/loader/a2t2t_loader.py
llm_agent_toolkit/loader/image_loader.py
llm_agent_toolkit-0.0.34.0.dist-info/LICENSE
llm_agent_toolkit-0.0.34.0.dist-info/METADATA
llm_agent_toolkit-0.0.34.0.dist-info/WHEEL
llm_agent_toolkit-0.0.34.0.dist-info/top_level.txt
llm_agent_toolkit-0.0.34.0.dist-info/RECORD
