Metadata-Version: 2.1
Name: llm-agent-toolkit
Version: 0.0.34.0
Summary: LLM Agent Toolkit provides minimal, modular interfaces for core components in LLM-based applications.
Author: jonah_whaler_2348
Author-email: jk_saga@proton.me
License: GPLv3
Keywords: llm,agent,toolkit,large language model,memory management,tool integration,multi-modality interaction,multi-step workflow,vision,tools,structured output,tts,text-to-speech,chunking,chromadb,faiss,ollama,openai,deepseek,elevenlabs
Classifier: Development Status :: 1 - Planning
Classifier: Intended Audience :: Developers
Classifier: License :: OSI Approved :: GNU General Public License v3 (GPLv3)
Classifier: Programming Language :: Python :: 3.10
License-File: LICENSE
Requires-Dist: python-dotenv==0.21.0
Requires-Dist: charade==1.0.3
Requires-Dist: openai==1.66.5
Requires-Dist: tiktoken==0.9.0
Requires-Dist: chromadb==0.5.11
Requires-Dist: faiss-cpu==1.9.0.post1
Requires-Dist: aiohttp==3.10.11
Requires-Dist: pdfplumber==0.11.4
Requires-Dist: PyMuPDF==1.24.11
Requires-Dist: python-docx==1.1.2
Provides-Extra: all
Requires-Dist: torch==2.6.0; extra == "all"
Requires-Dist: transformers==4.50.0; extra == "all"
Requires-Dist: pydub==0.25.1; extra == "all"
Requires-Dist: pydub-stubs==0.25.1.4; extra == "all"
Requires-Dist: ffmpeg-python==0.2.0; extra == "all"
Requires-Dist: setuptools-rust==1.10.2; extra == "all"
Requires-Dist: openai-whisper==20240930; extra == "all"
Requires-Dist: google-genai==1.0.0; extra == "all"
Requires-Dist: ollama==0.4.4; extra == "all"
Requires-Dist: elevenlabs==1.58.1; extra == "all"
Provides-Extra: elevenlabs
Requires-Dist: elevenlabs==1.58.1; extra == "elevenlabs"
Provides-Extra: gemini
Requires-Dist: google-genai==1.0.0; extra == "gemini"
Provides-Extra: ollama
Requires-Dist: ollama==0.4.4; extra == "ollama"
Provides-Extra: transcriber
Requires-Dist: pydub==0.25.1; extra == "transcriber"
Requires-Dist: pydub-stubs==0.25.1.4; extra == "transcriber"
Requires-Dist: ffmpeg-python==0.2.0; extra == "transcriber"
Requires-Dist: setuptools-rust==1.10.2; extra == "transcriber"
Requires-Dist: openai-whisper==20240930; extra == "transcriber"
Provides-Extra: transformers
Requires-Dist: torch==2.6.0; extra == "transformers"
Requires-Dist: transformers==4.50.0; extra == "transformers"
